quickstatements/__init__.py
quickstatements/test.py
quickstatements-0.0.2.dist-info/METADATA
quickstatements-0.0.2.dist-info/WHEEL
quickstatements-0.0.2.dist-info/top_level.txt
quickstatements-0.0.2.dist-info/RECORD
