Metadata-Version: 2.1
Name: quickstatements
Version: 0.0.2
Summary: Facilitates the generation of Quickstatements V1 commands in Python.
Home-page: https://github.com/lubianat/quickstatements
Author: Tiago Lubiana
Author-email: tiago.lubiana.alves@usp.br
License: UNKNOWN
Platform: UNKNOWN
Classifier: Programming Language :: Python :: 3
Classifier: License :: OSI Approved :: MIT License
Classifier: Operating System :: OS Independent
